fp_ops/__init__.py
fp_ops/composition.py
fp_ops/context.py
fp_ops/decorators.py
fp_ops/execution.py
fp_ops/flow.py
fp_ops/graph.py
fp_ops/objects.py
fp_ops/operator.py
fp_ops/placeholder.py
fp_ops/primitives.py
fp_ops/py.typed
fp_ops/sequences.py
fp_ops/text.py
fp_ops/utils.py
fp_ops-0.2.11.dist-info/LICENSE
fp_ops-0.2.11.dist-info/METADATA
fp_ops-0.2.11.dist-info/WHEEL
fp_ops-0.2.11.dist-info/RECORD
