Metadata-Version: 2.3
Name: fp-ops
Version: 0.2.11
Summary: an ergonomic wrapper around the expression library
License: MIT
Author: Galad Dirie
Author-email: hello@galad.ca
Requires-Python: >=3.10,<4.0
Classifier: Development Status :: 4 - Beta
Classifier: Intended Audience :: Developers
Classifier: License :: OSI Approved :: MIT License
Classifier: Programming Language :: Python :: 3
Classifier: Programming Language :: Python :: 3.11
Classifier: Programming Language :: Python :: 3.12
Classifier: Programming Language :: Python :: 3.13
Classifier: Topic :: Software Development :: Libraries :: Python Modules
Requires-Dist: expression (>=5.6.0,<6.0.0)
Requires-Dist: pydantic (>=2.11.3,<3.0.0)
Project-URL: Bug Tracker, https://github.com/galaddirie/fp-ops/issues
Project-URL: GitHub, https://github.com/galaddirie/fp-ops
